pynamodb_rest/__init__.py
pynamodb_rest/pynamodb_rest.py
pynamodb_rest-0.0.3.dist-info/AUTHORS.rst
pynamodb_rest-0.0.3.dist-info/LICENSE
pynamodb_rest-0.0.3.dist-info/METADATA
pynamodb_rest-0.0.3.dist-info/WHEEL
pynamodb_rest-0.0.3.dist-info/top_level.txt
pynamodb_rest-0.0.3.dist-info/RECORD
