Metadata-Version: 2.1
Name: pynamodb-rest
Version: 0.0.3
Summary: A Python based project to easily serve up serverless REST apis utilizing the wonderful Pynamodb package
Home-page: https://github.com/ndanielsen/pynamodb_rest
Author: Nathan Danielsen
Author-email: nathan.danielsen@gmail.com
License: MIT license
Keywords: pynamodb_rest
Platform: UNKNOWN
Classifier: Development Status :: 2 - Pre-Alpha
Classifier: Intended Audience :: Developers
Classifier: License :: OSI Approved :: MIT License
Classifier: Natural Language :: English
Classifier: Programming Language :: Python :: 3
Classifier: Programming Language :: Python :: 3.5
Classifier: Programming Language :: Python :: 3.6
Classifier: Programming Language :: Python :: 3.7
Classifier: Programming Language :: Python :: 3.8
Requires-Python: !=3.0.*, !=3.1.*, !=3.2.*, !=3.3.*, !=3.4.*
